endura_sdk/__init__.py
endura_sdk-0.1.8.dist-info/licenses/LICENSE
endura_sdk-0.1.8.dist-info/METADATA
endura_sdk-0.1.8.dist-info/WHEEL
endura_sdk-0.1.8.dist-info/top_level.txt
endura_sdk-0.1.8.dist-info/RECORD
