Metadata-Version: 2.4
Name: endura-sdk
Version: 0.1.8
Summary: SDK for Edge AI Device Agent
Author-email: Michael Kirschbaum <hi@michaelkirschbaum.com>
Requires-Python: >=3.7
License-File: LICENSE
Requires-Dist: torch>=2.0
Requires-Dist: psutil
Requires-Dist: numpy
Requires-Dist: httpx>=0.27.0
Provides-Extra: dev
Requires-Dist: pytest>=8.1.1; extra == "dev"
Requires-Dist: pytest-asyncio; extra == "dev"
Requires-Dist: python-dotenv; extra == "dev"
Dynamic: license-file
